picas/LICENSE
picas/__init__.py
picas/actors.py
picas/apps/__init__.py
picas/apps/picas_cli.py
picas/clients.py
picas/couchdblogger.py
picas/crypto.py
picas/documents.py
picas/executers.py
picas/generators.py
picas/iterators.py
picas/jobid.py
picas/metadata.py
picas/modifiers.py
picas/picas_config.py
picas/picaslogger.py
picas/srm.py
picas/srmclient.py
picas/util.py
picas-1.1.0.dist-info/LICENSE
picas-1.1.0.dist-info/METADATA
picas-1.1.0.dist-info/WHEEL
picas-1.1.0.dist-info/entry_points.txt
picas-1.1.0.dist-info/RECORD
