Metadata-Version: 2.1
Name: picas
Version: 1.1.0
Summary: Python client using CouchDB as a token pool server.
License: MIT
Author: Jan Bot, Joris Borgdorff, Lodewijk Nauta, Haili Hu
Requires-Python: >=3.10,<4.0
Classifier: License :: OSI Approved :: MIT License
Classifier: Programming Language :: Python :: 3
Classifier: Programming Language :: Python :: 3.10
Classifier: Programming Language :: Python :: 3.11
Classifier: Programming Language :: Python :: 3.12
Classifier: Programming Language :: Python :: 3.13
Requires-Dist: PyYAML (>=6.0.2,<7.0.0)
Requires-Dist: couchdb (>=1.2,<2.0)
Requires-Dist: cryptography (>=41.0.4,<42.0.0)
Requires-Dist: ipykernel (>=6.24.0,<7.0.0)
Requires-Dist: jsonschema (>=4.19.0,<5.0.0)
Requires-Dist: requests (>=2.31.0,<3.0.0)
Requires-Dist: setuptools (>=80,<81)
Requires-Dist: stopit (>=1.1.2,<2.0.0)
